django_wso2is/__init__.py
django_wso2is/apps.py
django_wso2is/authentication.py
django_wso2is/backends.py
django_wso2is/conf.py
django_wso2is/errors.py
django_wso2is/signals.py
django_wso2is/token.py
django_wso2is/utils.py
django_wso2is/api/__init__.py
django_wso2is/api/serializers.py
django_wso2is/api/urls.py
django_wso2is/api/views.py
django_wso2is/management/__init__.py
django_wso2is/management/commands/__init__.py
django_wso2is/management/commands/sync_wso2is_users.py
django_wso2is_auth-0.0.1.dist-info/LICENCE
django_wso2is_auth-0.0.1.dist-info/METADATA
django_wso2is_auth-0.0.1.dist-info/WHEEL
django_wso2is_auth-0.0.1.dist-info/top_level.txt
django_wso2is_auth-0.0.1.dist-info/RECORD
