Metadata-Version: 2.1
Name: django-wso2is-auth
Version: 0.0.1
Summary: Django authentication against WSO2 Identity Server
Author-email: Ubiwhere <geral@ubiwhere.com>
Project-URL: Homepage, https://github.com/Ubiwhere/django-wso2is-auth/
Project-URL: Bug Tracker, https://github.com/Ubiwhere/django-wso2is-auth/issues
Classifier: Programming Language :: Python :: 3
Classifier: License :: OSI Approved :: MIT License
Classifier: Operating System :: OS Independent
Requires-Python: >=3.8
License-File: LICENCE
Requires-Dist: django (<4.2,>=3.2)
Requires-Dist: requests (==2.28.2)
Requires-Dist: djangorestframework (<3.15,>=3.14)
Requires-Dist: jsonpath-ng (==1.5.3)
